LICENSE.txt
MANIFEST.in
README.rst
setup.py
bash_completion.d/sftpman
sftpman/__init__.py
sftpman/cli.py
sftpman/exception.py
sftpman/helper.py
sftpman/launcher.py
sftpman/model.py
sftpman.egg-info/PKG-INFO
sftpman.egg-info/SOURCES.txt
sftpman.egg-info/dependency_links.txt
sftpman.egg-info/entry_points.txt
sftpman.egg-info/not-zip-safe
sftpman.egg-info/top_level.txt
sleep-scripts/sleep.d/49-sftpman-unmount-all
sleep-scripts/system-sleep/sftpman-unmount-all.sh